{"formatName":"dexie","formatVersion":1,"data":{"databaseName":"sync","databaseVersion":2,"tables":[{"name":"example_table","schema":"localUUID,objectStatus,changes,record,lastModified,lastRequestUuid,retries","rowCount":0},{"name":"testEntity","schema":"localUUID,changes,lastModified,record,objectStatus,lastRequestUuid,retries","rowCount":5}],"data":[{"tableName":"example_table","inbound":true,"rows":[]},{"tableName":"testEntity","inbound":true,"rows":[{"localUUID":"31f7fcec-1585-4bd1-8952-c09fc7576b81","changes":[],"lastRequestUuid":null,"record":{"id":1009,"uuid":"31f7fcec-1585-4bd1-8952-c09fc7576b81","firstInput":"FI:11_3","secondInput":"SI: 11_3","lastModified":1693816602000},"objectStatus":"synced","lastModified":1693816602000,"retries":0,"$types":{"changes":"arrayNonindexKeys","record.lastModified":"date","lastModified":"date"}},{"localUUID":"34e74808-68c7-4380-99ac-7a6dbc53055d","changes":[],"lastRequestUuid":null,"record":{"id":1010,"uuid":"34e74808-68c7-4380-99ac-7a6dbc53055d","firstInput":"FI:11_1","secondInput":"SI: 11_1","lastModified":1693816602000},"objectStatus":"synced","lastModified":1693816602000,"retries":0,"$types":{"changes":"arrayNonindexKeys","record.lastModified":"date","lastModified":"date"}},{"localUUID":"3a9509da-700e-4469-a72a-654daa395f71_shared","changes":[],"lastRequestUuid":null,"record":{"id":1011,"uuid":"3a9509da-700e-4469-a72a-654daa395f71_shared","firstInput":"FI:11_0","secondInput":"SI: 11_0","lastModified":1693816602000},"objectStatus":"synced","lastModified":1693816602000,"retries":0,"$types":{"changes":"arrayNonindexKeys","record.lastModified":"date","lastModified":"date"}},{"localUUID":"53948115-b648-4979-8ead-ee6c2720f5c9_shared","changes":[],"lastRequestUuid":null,"record":{"id":1012,"uuid":"53948115-b648-4979-8ead-ee6c2720f5c9_shared","firstInput":"FI:11_4","secondInput":"SI: 11_4","lastModified":1693816602000},"objectStatus":"synced","lastModified":1693816602000,"retries":0,"$types":{"changes":"arrayNonindexKeys","record.lastModified":"date","lastModified":"date"}},{"localUUID":"5e1198d6-5eaa-4833-be3b-23b0a96b0913_shared","changes":[],"lastRequestUuid":null,"record":{"id":1013,"uuid":"5e1198d6-5eaa-4833-be3b-23b0a96b0913_shared","firstInput":"FI:11_2","secondInput":"SI: 11_2","lastModified":1693816602000},"objectStatus":"synced","lastModified":1693816602000,"retries":0,"$types":{"changes":"arrayNonindexKeys","record.lastModified":"date","lastModified":"date"}}]}]}}